zdiab_tools/Automate_func.py
zdiab_tools/__init__.py
zdiab_tools-0.3.dist-info/METADATA
zdiab_tools-0.3.dist-info/WHEEL
zdiab_tools-0.3.dist-info/top_level.txt
zdiab_tools-0.3.dist-info/RECORD
