Metadata-Version: 2.1
Name: zdiab-tools
Version: 0.3
Summary: Rasa preprocessing package
Author: zohair diab
Author-email: zohairdiab07@gmail.com
